README.md
pyproject.toml
openet/__init__.py
openet/lst/__init__.py
openet/lst/landsat.py
openet/lst/model.py
openet/lst/tests/conftest.py
openet/lst/tests/test_landsat.py
openet/lst/tests/test_model.py
openet_landsat_lst.egg-info/PKG-INFO
openet_landsat_lst.egg-info/SOURCES.txt
openet_landsat_lst.egg-info/dependency_links.txt
openet_landsat_lst.egg-info/requires.txt
openet_landsat_lst.egg-info/top_level.txt