Metadata-Version: 2.1
Name: openet-landsat-lst
Version: 0.2.0
Summary: Earth Engine based Landsat LST sharpening functions
Author-email: Yanghui Kang <ykang38@wisc.edu>, Yun Yang <yun.yang@msstate.edu>
Maintainer-email: Charles Morton <charles.morton@dri.edu>
License: Apache-2.0
Project-URL: Homepage, https://github.com/Open-ET/openet-landsat-lst
Keywords: LST,OpenET,Earth Engine,Evapotranspiration,Landsat
Classifier: Programming Language :: Python :: 3
Classifier: License :: OSI Approved :: Apache Software License
Classifier: Operating System :: OS Independent
Requires-Python: >=3.8
Requires-Dist: earthengine-api>=0.1.367
Requires-Dist: openet-core>=0.2.0
Provides-Extra: test
Requires-Dist: pytest; extra == "test"
